RISC - V/data_mem.v
`timescale 1ns / 1ps
//////////////////////////////////////////////////////////////////////////////////
// Company: 
// Engineer: 
// 
// Create Date: 05/23/2026 01:29:15 PM
// Design Name: 
// Module Name: data_mem
// Project Name: 
// Target Devices: 
// Tool Versions: 
// Description: 
// 
// Dependencies: 
// 
// Revision:
// Revision 0.01 - File Created
// Additional Comments:
// 
//////////////////////////////////////////////////////////////////////////////////


module data_mem (
    input  wire        clk,
    input  wire        reset,
    input  wire        mem_read,
    input  wire        mem_write,
    input  wire [2:0]  funct3,
    input  wire [31:0] addr,
    input  wire [31:0] write_data,
    output reg  [31:0] read_data
);

    localparam DEPTH = 1024; // 4 KiB
    reg [7:0] mem [0:DEPTH-1];

    integer i;
    wire [9:0] word_index = addr[11:2];

    always @(posedge clk) begin
        if (reset) begin
            for (i = 0; i < DEPTH; i = i + 1)
                mem[i] <= 8'd0;
        end else if (mem_write) begin
            case (funct3)
                3'b000: mem[addr[11:0]] <= write_data[7:0];                    // SB
                3'b001: begin                                                  // SH
                    mem[addr[11:0]]     <= write_data[7:0];
                    mem[addr[11:0] + 1] <= write_data[15:8];
                end
                3'b010: begin                                                  // SW
                    mem[addr[11:0]]     <= write_data[7:0];
                    mem[addr[11:0] + 1] <= write_data[15:8];
                    mem[addr[11:0] + 2] <= write_data[23:16];
                    mem[addr[11:0] + 3] <= write_data[31:24];
                end
                default: ;
            endcase
        end
    end

    wire [7:0]  byte_val  = mem[addr[11:0]];
    wire [15:0] half_val  = {mem[addr[11:0] + 1], mem[addr[11:0]]};
    wire [31:0] word_val  = {mem[addr[11:0] + 3], mem[addr[11:0] + 2],
                             mem[addr[11:0] + 1], mem[addr[11:0]]};

    always @(*) begin
        if (!mem_read) begin
            read_data = 32'd0;
        end else begin
            case (funct3)
                3'b000: read_data = {{24{byte_val[7]}}, byte_val};             // LB
                3'b001: read_data = {{16{half_val[15]}}, half_val};            // LH
                3'b010: read_data = word_val;                                    // LW
                3'b100: read_data = {24'd0, byte_val};                         // LBU
                3'b101: read_data = {16'd0, half_val};                           // LHU
                default: read_data = word_val;
            endcase
        end
    end

endmodule

RISC - V/branch_unit.v
`timescale 1ns / 1ps
//////////////////////////////////////////////////////////////////////////////////
// Company: 
// Engineer: 
// 
// Create Date: 05/23/2026 01:27:40 PM
// Design Name: 
// Module Name: branch_unit
// Project Name: 
// Target Devices: 
// Tool Versions: 
// Description: 
// 
// Dependencies: 
// 
// Revision:
// Revision 0.01 - File Created
// Additional Comments:
// 
//////////////////////////////////////////////////////////////////////////////////

module branch_unit (
    input  wire [31:0] rs1,
    input  wire [31:0] rs2,
    input  wire [2:0]  branch_type,
    output wire        taken
);

    localparam BR_EQ  = 3'd0;
    localparam BR_NE  = 3'd1;
    localparam BR_LT  = 3'd2;
    localparam BR_GE  = 3'd3;
    localparam BR_LTU = 3'd4;
    localparam BR_GEU = 3'd5;

    reg branch_taken;

    always @(*) begin
        case (branch_type)
            BR_EQ:  branch_taken = (rs1 == rs2);
            BR_NE:  branch_taken = (rs1 != rs2);
            BR_LT:  branch_taken = ($signed(rs1) < $signed(rs2));
            BR_GE:  branch_taken = ($signed(rs1) >= $signed(rs2));
            BR_LTU: branch_taken = (rs1 < rs2);
            BR_GEU: branch_taken = (rs1 >= rs2);
            default: branch_taken = 1'b0;
        endcase
    end

    assign taken = branch_taken;

endmodule

RISC - V/alu.v
`timescale 1ns / 1ps
//////////////////////////////////////////////////////////////////////////////////
// Company: 
// Engineer: 
// 
// Create Date: 05/23/2026 01:18:57 PM
// Design Name: 
// Module Name: alu
// Project Name: 
// Target Devices: 
// Tool Versions: 
// Description: 
// 
// Dependencies: 
// 
// Revision:
// Revision 0.01 - File Created
// Additional Comments:
// 
//////////////////////////////////////////////////////////////////////////////////


// RV32I ALU - arithmetic and logical operations
module alu (
    input  wire [31:0] a,
    input  wire [31:0] b,
    input  wire [3:0]  alu_ctrl,
    output reg  [31:0] result
);

    localparam ALU_ADD  = 4'd0;
    localparam ALU_SUB  = 4'd1;
    localparam ALU_SLL  = 4'd2;
    localparam ALU_SLT  = 4'd3;
    localparam ALU_SLTU = 4'd4;
    localparam ALU_XOR  = 4'd5;
    localparam ALU_SRL  = 4'd6;
    localparam ALU_SRA  = 4'd7;
    localparam ALU_OR   = 4'd8;
    localparam ALU_AND  = 4'd9;
    localparam ALU_PASS = 4'd10; // pass B (for LUI path via imm)

    wire [31:0] sum = a + b;

    always @(*) begin
        case (alu_ctrl)
            ALU_ADD:  result = sum;
            ALU_SUB:  result = a - b;
            ALU_SLL:  result = a << b[4:0];
            ALU_SLT:  result = ($signed(a) < $signed(b)) ? 32'd1 : 32'd0;
            ALU_SLTU: result = (a < b) ? 32'd1 : 32'd0;
            ALU_XOR:  result = a ^ b;
            ALU_SRL:  result = a >> b[4:0];
            ALU_SRA:  result = $signed(a) >>> b[4:0];
            ALU_OR:   result = a | b;
            ALU_AND:  result = a & b;
            ALU_PASS: result = b;
            default:  result = 32'd0;
        endcase
    end

endmodule

RISC - V/regfile.v
`timescale 1ns / 1ps
//////////////////////////////////////////////////////////////////////////////////
// Company: 
// Engineer: 
// 
// Create Date: 05/23/2026 01:33:54 PM
// Design Name: 
// Module Name: regfile
// Project Name: 
// Target Devices: 
// Tool Versions: 
// Description: 
// 
// Dependencies: 
// 
// Revision:
// Revision 0.01 - File Created
// Additional Comments:
// 
//////////////////////////////////////////////////////////////////////////////////


module regfile (
    input  wire        clk,
    input  wire        reset,
    input  wire        reg_write,
    input  wire [4:0]  rd_addr,
    input  wire [31:0] rd_data,
    input  wire [4:0]  rs1_addr,
    input  wire [4:0]  rs2_addr,
    output wire [31:0] rs1_data,
    output wire [31:0] rs2_data
);

    reg [31:0] regs [1:31]; // x1-x31; x0 is always 0

    integer i;

    assign rs1_data = (rs1_addr == 5'd0) ? 32'd0 : regs[rs1_addr];
    assign rs2_data = (rs2_addr == 5'd0) ? 32'd0 : regs[rs2_addr];

    always @(posedge clk) begin
        if (reset) begin
            for (i = 1; i < 32; i = i + 1)
                regs[i] <= 32'd0;
        end else if (reg_write && (rd_addr != 5'd0)) begin
            regs[rd_addr] <= rd_data;
        end
    end

endmodule

RISC - V/imm_gen.v
`timescale 1ns / 1ps
//////////////////////////////////////////////////////////////////////////////////
// Company: 
// Engineer: 
// 
// Create Date: 05/23/2026 01:24:36 PM
// Design Name: 
// Module Name: imm_gen
// Project Name: 
// Target Devices: 
// Tool Versions: 
// Description: 
// 
// Dependencies: 
// 
// Revision:
// Revision 0.01 - File Created
// Additional Comments:
// 
//////////////////////////////////////////////////////////////////////////////////

module imm_gen (
    input  wire [31:0] instr,
    input  wire [2:0]  imm_type,
    output reg  [31:0] imm
);

    localparam IMM_I = 3'd0;
    localparam IMM_S = 3'd1;
    localparam IMM_B = 3'd2;
    localparam IMM_U = 3'd3;
    localparam IMM_J = 3'd4;

    wire [31:0] i_imm = {{20{instr[31]}}, instr[31:20]};
    wire [31:0] s_imm = {{20{instr[31]}}, instr[31:25], instr[11:7]};
    wire [31:0] b_imm = {{19{instr[31]}}, instr[31],
                         instr[7], instr[30:25], instr[11:8], 1'b0};
    wire [31:0] u_imm = {instr[31:12], 12'b0};
    wire [31:0] j_imm = {{11{instr[31]}}, instr[31],
                         instr[19:12], instr[20], instr[30:21], 1'b0};

    always @(*) begin
        case (imm_type)
            IMM_I: imm = i_imm;
            IMM_S: imm = s_imm;
            IMM_B: imm = b_imm;
            IMM_U: imm = u_imm;
            IMM_J: imm = j_imm;
            default: imm = 32'd0;
        endcase
    end

endmodule

RISC - V/control.v
`timescale 1ns / 1ps
//////////////////////////////////////////////////////////////////////////////////
// Company: 
// Engineer: 
// 
// Create Date: 05/23/2026 01:26:22 PM
// Design Name: 
// Module Name: control
// Project Name: 
// Target Devices: 
// Tool Versions: 
// Description: 
// 
// Dependencies: 
// 
// Revision:
// Revision 0.01 - File Created
// Additional Comments:
// 
//////////////////////////////////////////////////////////////////////////////////

module control (
    input  wire [6:0] opcode,
    input  wire [2:0] funct3,
    input  wire [6:0] funct7,
    output reg        reg_write,
    output reg        mem_read,
    output reg        mem_write,
    output reg        branch,
    output reg        jump,
    output reg        jalr,
    output reg        alu_src,
    output reg        mem_to_reg,
    output reg        auipc,
    output reg        lui,
    output reg [2:0]  imm_type,
    output reg [3:0]  alu_ctrl,
    output reg [2:0]  branch_type
);

    localparam OPCODE_LOAD    = 7'b0000011;
    localparam OPCODE_OP_IMM  = 7'b0010011;
    localparam OPCODE_AUIPC   = 7'b0010111;
    localparam OPCODE_STORE   = 7'b0100011;
    localparam OPCODE_OP      = 7'b0110011;
    localparam OPCODE_LUI     = 7'b0110111;
    localparam OPCODE_BRANCH  = 7'b1100011;
    localparam OPCODE_JALR    = 7'b1100111;
    localparam OPCODE_JAL     = 7'b1101111;

    localparam IMM_I = 3'd0;
    localparam IMM_S = 3'd1;
    localparam IMM_B = 3'd2;
    localparam IMM_U = 3'd3;
    localparam IMM_J = 3'd4;

    localparam ALU_ADD  = 4'd0;
    localparam ALU_SUB  = 4'd1;
    localparam ALU_SLL  = 4'd2;
    localparam ALU_SLT  = 4'd3;
    localparam ALU_SLTU = 4'd4;
    localparam ALU_XOR  = 4'd5;
    localparam ALU_SRL  = 4'd6;
    localparam ALU_SRA  = 4'd7;
    localparam ALU_OR   = 4'd8;
    localparam ALU_AND  = 4'd9;
    localparam ALU_PASS = 4'd10;

    localparam BR_EQ  = 3'd0;
    localparam BR_NE  = 3'd1;
    localparam BR_LT  = 3'd2;
    localparam BR_GE  = 3'd3;
    localparam BR_LTU = 3'd4;
    localparam BR_GEU = 3'd5;

    always @(*) begin
        reg_write   = 1'b0;
        mem_read    = 1'b0;
        mem_write   = 1'b0;
        branch      = 1'b0;
        jump        = 1'b0;
        jalr        = 1'b0;
        alu_src     = 1'b0;
        mem_to_reg  = 1'b0;
        auipc       = 1'b0;
        lui         = 1'b0;
        imm_type    = IMM_I;
        alu_ctrl    = ALU_ADD;
        branch_type = BR_EQ;

        case (opcode)
            OPCODE_LUI: begin
                reg_write = 1'b1;
                alu_src   = 1'b1;
                lui       = 1'b1;
                imm_type  = IMM_U;
                alu_ctrl  = ALU_PASS;
            end

            OPCODE_AUIPC: begin
                reg_write = 1'b1;
                alu_src   = 1'b1;
                auipc     = 1'b1;
                imm_type  = IMM_U;
                alu_ctrl  = ALU_ADD;
            end

            OPCODE_JAL: begin
                reg_write = 1'b1;
                jump      = 1'b1;
                imm_type  = IMM_J;
            end

            OPCODE_JALR: begin
                reg_write = 1'b1;
                jump      = 1'b1;
                jalr      = 1'b1;
                alu_src   = 1'b1;
                imm_type  = IMM_I;
                alu_ctrl  = ALU_ADD;
            end

            OPCODE_BRANCH: begin
                branch      = 1'b1;
                imm_type    = IMM_B;
                branch_type = funct3;
            end

            OPCODE_LOAD: begin
                reg_write  = 1'b1;
                mem_read   = 1'b1;
                alu_src    = 1'b1;
                mem_to_reg = 1'b1;
                imm_type   = IMM_I;
                alu_ctrl   = ALU_ADD;
            end

            OPCODE_STORE: begin
                mem_write = 1'b1;
                alu_src   = 1'b1;
                imm_type  = IMM_S;
                alu_ctrl  = ALU_ADD;
            end

            OPCODE_OP_IMM: begin
                reg_write = 1'b1;
                alu_src   = 1'b1;
                imm_type  = IMM_I;
                case (funct3)
                    3'b000: alu_ctrl = ALU_ADD;
                    3'b010: alu_ctrl = ALU_SLT;
                    3'b011: alu_ctrl = ALU_SLTU;
                    3'b100: alu_ctrl = ALU_XOR;
                    3'b110: alu_ctrl = ALU_OR;
                    3'b111: alu_ctrl = ALU_AND;
                    3'b001: alu_ctrl = ALU_SLL;
                    3'b101: alu_ctrl = (funct7[5]) ? ALU_SRA : ALU_SRL;
                    default: alu_ctrl = ALU_ADD;
                endcase
            end

            OPCODE_OP: begin
                reg_write = 1'b1;
                case (funct3)
                    3'b000: alu_ctrl = (funct7[5]) ? ALU_SUB : ALU_ADD;
                    3'b001: alu_ctrl = ALU_SLL;
                    3'b010: alu_ctrl = ALU_SLT;
                    3'b011: alu_ctrl = ALU_SLTU;
                    3'b100: alu_ctrl = ALU_XOR;
                    3'b101: alu_ctrl = (funct7[5]) ? ALU_SRA : ALU_SRL;
                    3'b110: alu_ctrl = ALU_OR;
                    3'b111: alu_ctrl = ALU_AND;
                    default: alu_ctrl = ALU_ADD;
                endcase
            end

            default: ;
        endcase
    end

endmodule

RISC - V/instr_mem.v
`timescale 1ns / 1ps
//////////////////////////////////////////////////////////////////////////////////
// Company: 
// Engineer: 
// 
// Create Date: 05/23/2026 01:36:15 PM
// Design Name: 
// Module Name: instr_mem
// Project Name: 
// Target Devices: 
// Tool Versions: 
// Description: 
// 
// Dependencies: 
// 
// Revision:
// Revision 0.01 - File Created
// Additional Comments:
// 
//////////////////////////////////////////////////////////////////////////////////

module instr_mem #(
    parameter DEPTH    = 256,
    parameter HEX_FILE = "programs/program.hex"
)(
    input  wire [31:0] addr,
    output wire [31:0] instr
);

    localparam ADDR_W = $clog2(DEPTH);

    reg [31:0] rom [0:DEPTH-1];

    integer i;

    initial begin
        for (i = 0; i < DEPTH; i = i + 1)
            rom[i] = 32'h00000013;

        $readmemh(HEX_FILE, rom);

`ifdef FALLBACK_PROG_VH
`include "program_init.vh"
`endif
    end

    wire [ADDR_W-1:0] word_addr = addr[ADDR_W+1:2];

    assign instr = rom[word_addr];

endmodule

RISC - V/rv32i_cpu.v
`timescale 1ns / 1ps
//////////////////////////////////////////////////////////////////////////////////
// Company: 
// Engineer: 
// 
// Create Date: 05/23/2026 01:32:31 PM
// Design Name: 
// Module Name: rv32i_cpu
// Project Name: 
// Target Devices: 
// Tool Versions: 
// Description: 
// 
// Dependencies: 
// 
// Revision:
// Revision 0.01 - File Created
// Additional Comments:
// 
//////////////////////////////////////////////////////////////////////////////////

// RV32I Single-Cycle Processor - top-level core
module rv32i_cpu (
    input  wire        clk,
    input  wire        reset,
    output wire [31:0] pc_out,
    output wire [31:0] instr_out,
    output wire [31:0] alu_result_out,
    output wire        reg_write_out
);

    reg [31:0] pc;

    wire [31:0] instr;
    wire [6:0]  opcode  = instr[6:0];
    wire [4:0]  rd      = instr[11:7];
    wire [2:0]  funct3  = instr[14:12];
    wire [4:0]  rs1     = instr[19:15];
    wire [4:0]  rs2     = instr[24:20];
    wire [6:0]  funct7  = instr[31:25];

    wire        reg_write, mem_read, mem_write, branch, jump, jalr;
    wire        alu_src, mem_to_reg, auipc, lui;
    wire [2:0]  imm_type, branch_type;
    wire [3:0]  alu_ctrl;

    wire [31:0] imm;
    wire [31:0] rs1_data, rs2_data;
    wire [31:0] alu_a, alu_b, alu_result;
    wire        branch_taken;
    wire [31:0] mem_rdata;
    wire [31:0] rd_wdata;
    wire [31:0] pc_plus4;
    wire [31:0] pc_next;

    assign pc_out          = pc;
    assign instr_out       = instr;
    assign alu_result_out  = alu_result;
    assign reg_write_out   = reg_write;

    assign pc_plus4 = pc + 32'd4;

    instr_mem u_imem (
        .addr (pc),
        .instr(instr)
    );

    control u_ctrl (
        .opcode      (opcode),
        .funct3      (funct3),
        .funct7      (funct7),
        .reg_write   (reg_write),
        .mem_read    (mem_read),
        .mem_write   (mem_write),
        .branch      (branch),
        .jump        (jump),
        .jalr        (jalr),
        .alu_src     (alu_src),
        .mem_to_reg  (mem_to_reg),
        .auipc       (auipc),
        .lui         (lui),
        .imm_type    (imm_type),
        .alu_ctrl    (alu_ctrl),
        .branch_type (branch_type)
    );

    imm_gen u_imm (
        .instr   (instr),
        .imm_type(imm_type),
        .imm     (imm)
    );

    regfile u_reg (
        .clk      (clk),
        .reset    (reset),
        .reg_write(reg_write),
        .rd_addr  (rd),
        .rd_data  (rd_wdata),
        .rs1_addr (rs1),
        .rs2_addr (rs2),
        .rs1_data (rs1_data),
        .rs2_data (rs2_data)
    );

    assign alu_a = auipc ? pc : rs1_data;
    assign alu_b = alu_src ? imm : rs2_data;

    alu u_alu (
        .a        (alu_a),
        .b        (alu_b),
        .alu_ctrl (alu_ctrl),
        .result   (alu_result)
    );

    branch_unit u_br (
        .rs1         (rs1_data),
        .rs2         (rs2_data),
        .branch_type (branch_type),
        .taken       (branch_taken)
    );

    data_mem u_dmem (
        .clk       (clk),
        .reset     (reset),
        .mem_read  (mem_read),
        .mem_write (mem_write),
        .funct3    (funct3),
        .addr      (alu_result),
        .write_data(rs2_data),
        .read_data (mem_rdata)
    );

    assign rd_wdata = jump ? pc_plus4 :
                      mem_to_reg ? mem_rdata : alu_result;

    wire [31:0] branch_target = pc + imm;
    wire [31:0] jalr_target = (rs1_data + imm) & ~32'd1;
    wire [31:0] jump_target = jalr ? jalr_target : (pc + imm);

    assign pc_next = jump ? jump_target :
                     (branch && branch_taken) ? branch_target :
                     pc_plus4;

    always @(posedge clk) begin
        if (reset)
            pc <= 32'd0;
        else
            pc <= pc_next;
    end

endmodule

RISC - V/tb_rv32i_cpu.v
`timescale 1ns / 1ps
//////////////////////////////////////////////////////////////////////////////////
// Company: 
// Engineer: 
// 
// Create Date: 05/23/2026 01:37:44 PM
// Design Name: 
// Module Name: tb_rv32i_cpu
// Project Name: 
// Target Devices: 
// Tool Versions: 
// Description: 
// 
// Dependencies: 
// 
// Revision:
// Revision 0.01 - File Created
// Additional Comments:
// 
//////////////////////////////////////////////////////////////////////////////////



module tb_rv32i_cpu;

    reg         clk;
    reg         reset;
    wire [31:0] pc;
    wire [31:0] instr;
    wire [31:0] alu_result;
    wire        reg_write;

    rv32i_cpu uut (
        .clk            (clk),
        .reset          (reset),
        .pc_out         (pc),
        .instr_out      (instr),
        .alu_result_out (alu_result),
        .reg_write_out  (reg_write)
    );

    initial begin
        clk = 1'b0;
        forever #5 clk = ~clk; // 100 MHz
    end

    initial begin
        $dumpfile("sim/rv32i_cpu.vcd");
        $dumpvars(0, tb_rv32i_cpu);
    end

    // Peek register file via hierarchical access
    wire [31:0] x1 = uut.u_reg.regs[1];
    wire [31:0] x2 = uut.u_reg.regs[2];
    wire [31:0] x3 = uut.u_reg.regs[3];
    wire [31:0] x4 = uut.u_reg.regs[4];
    wire [31:0] x5 = uut.u_reg.regs[5];
    wire [31:0] x6 = uut.u_reg.regs[6];
    wire [31:0] x7 = uut.u_reg.regs[7];

    integer errors;

    initial begin
        errors = 0;
        reset = 1'b1;
        #25;
        reset = 1'b0;

        // Wait for program to reach halt (10 instructions + pipeline settle)
        repeat (20) @(posedge clk);

        $display("=== RV32I CPU Simulation Results ===");
        $display(" PC        = 0x%08h", pc);
        $display(" x1 (5)    = %0d (expected 5)",  x1);
        $display(" x2 (3)    = %0d (expected 3)",  x2);
        $display(" x3 (8)    = %0d (expected 8)",  x3);
        $display(" x4 (8)    = %0d (expected 8)",  x4);
        $display(" x5 (skip) = %0d (expected 0)", x5);
        $display(" x6 (flag) = %0d (expected 1)",  x6);
        $display(" x7 (42)   = %0d (expected 42)", x7);

        if (x1 !== 32'd5)  begin $display("FAIL: x1"); errors = errors + 1; end
        if (x2 !== 32'd3)  begin $display("FAIL: x2"); errors = errors + 1; end
        if (x3 !== 32'd8)  begin $display("FAIL: x3"); errors = errors + 1; end
        if (x4 !== 32'd8)  begin $display("FAIL: x4"); errors = errors + 1; end
        if (x5 !== 32'd0)  begin $display("FAIL: x5 (branch did not skip)"); errors = errors + 1; end
        if (x6 !== 32'd1)  begin $display("FAIL: x6"); errors = errors + 1; end
        if (x7 !== 32'd42) begin $display("FAIL: x7"); errors = errors + 1; end

        if (errors == 0)
            $display("*** ALL TESTS PASSED ***");
        else
            $display("*** %0d TEST(S) FAILED ***", errors);

        $finish;
    end

endmodule

RISC - V/dump.vcd
$date
   Sat May 23 18:53:42 2026
$end

$version
  2023.2
$end

$timescale
  1ps
$end

$scope module tb_rv32i_cpu $end
$var reg 1 ! clk $end
$var reg 1 " reset $end
$var wire 32 # pc [31:0] $end
$var wire 32 $ instr [31:0] $end
$var wire 32 % alu_result [31:0] $end
$var wire 1 & reg_write $end
$var wire 32 ' x1 [31:0] $end
$var wire 32 ( x2 [31:0] $end
$var wire 32 ) x3 [31:0] $end
$var wire 32 * x4 [31:0] $end
$var wire 32 + x5 [31:0] $end
$var wire 32 , x6 [31:0] $end
$var wire 32 - x7 [31:0] $end
$var integer 32 . errors [31:0] $end
$scope module uut $end
$var wire 1 / clk $end
$var wire 1 0 reset $end
$var wire 32 # pc_out [31:0] $end
$var wire 32 $ instr_out [31:0] $end
$var wire 32 % alu_result_out [31:0] $end
$var wire 1 & reg_write_out $end
$var reg 32 1 pc [31:0] $end
$var wire 32 2 instr [31:0] $end
$var wire 7 3 opcode [6:0] $end
$var wire 5 4 rd [4:0] $end
$var wire 3 5 funct3 [2:0] $end
$var wire 5 6 rs1 [4:0] $end
$var wire 5 7 rs2 [4:0] $end
$var wire 7 8 funct7 [6:0] $end
$var wire 1 9 reg_write $end
$var wire 1 : mem_read $end
$var wire 1 ; mem_write $end
$var wire 1 < branch $end
$var wire 1 = jump $end
$var wire 1 > jalr $end
$var wire 1 ? alu_src $end
$var wire 1 @ mem_to_reg $end
$var wire 1 A auipc $end
$var wire 1 B lui $end
$var wire 3 C imm_type [2:0] $end
$var wire 3 D branch_type [2:0] $end
$var wire 4 E alu_ctrl [3:0] $end
$var wire 32 F imm [31:0] $end
$var wire 32 G rs1_data [31:0] $end
$var wire 32 H rs2_data [31:0] $end
$var wire 32 I alu_a [31:0] $end
$var wire 32 J alu_b [31:0] $end
$var wire 32 K alu_result [31:0] $end
$var wire 1 L branch_taken $end
$var wire 32 M mem_rdata [31:0] $end
$var wire 32 N rd_wdata [31:0] $end
$var wire 32 O pc_plus4 [31:0] $end
$var wire 32 P pc_next [31:0] $end
$var wire 32 Q branch_target [31:0] $end
$var wire 32 R jalr_target [31:0] $end
$var wire 32 S jump_target [31:0] $end
$scope module u_imem $end
$var wire 32 T addr [31:0] $end
$var wire 32 2 instr [31:0] $end
$var integer 32 U i [31:0] $end
$var wire 8 V word_addr [7:0] $end
$upscope $end
$scope module u_ctrl $end
$var wire 7 3 opcode [6:0] $end
$var wire 3 5 funct3 [2:0] $end
$var wire 7 8 funct7 [6:0] $end
$var reg 1 W reg_write $end
$var reg 1 X mem_read $end
$var reg 1 Y mem_write $end
$var reg 1 Z branch $end
$var reg 1 [ jump $end
$var reg 1 \ jalr $end
$var reg 1 ] alu_src $end
$var reg 1 ^ mem_to_reg $end
$var reg 1 _ auipc $end
$var reg 1 ` lui $end
$var reg 3 a imm_type [2:0] $end
$var reg 4 b alu_ctrl [3:0] $end
$var reg 3 c branch_type [2:0] $end
$upscope $end
$scope module u_imm $end
$var wire 32 2 instr [31:0] $end
$var wire 3 C imm_type [2:0] $end
$var reg 32 d imm [31:0] $end
$var wire 32 e i_imm [31:0] $end
$var wire 32 f s_imm [31:0] $end
$var wire 32 g b_imm [31:0] $end
$var wire 32 h u_imm [31:0] $end
$var wire 32 i j_imm [31:0] $end
$upscope $end
$scope module u_reg $end
$var wire 1 / clk $end
$var wire 1 0 reset $end
$var wire 1 9 reg_write $end
$var wire 5 4 rd_addr [4:0] $end
$var wire 32 N rd_data [31:0] $end
$var wire 5 6 rs1_addr [4:0] $end
$var wire 5 7 rs2_addr [4:0] $end
$var wire 32 G rs1_data [31:0] $end
$var wire 32 H rs2_data [31:0] $end
$var integer 32 j i [31:0] $end
$upscope $end
$scope module u_alu $end
$var wire 32 I a [31:0] $end
$var wire 32 J b [31:0] $end
$var wire 4 E alu_ctrl [3:0] $end
$var reg 32 k result [31:0] $end
$var wire 32 l sum [31:0] $end
$upscope $end
$scope module u_br $end
$var wire 32 G rs1 [31:0] $end
$var wire 32 H rs2 [31:0] $end
$var wire 3 D branch_type [2:0] $end
$var wire 1 L taken $end
$var reg 1 m branch_taken $end
$upscope $end
$scope module u_dmem $end
$var wire 1 / clk $end
$var wire 1 0 reset $end
$var wire 1 : mem_read $end
$var wire 1 ; mem_write $end
$var wire 3 5 funct3 [2:0] $end
$var wire 32 K addr [31:0] $end
$var wire 32 H write_data [31:0] $end
$var reg 32 n read_data [31:0] $end
$var integer 32 o i [31:0] $end
$var wire 10 p word_index [9:0] $end
$var wire 8 q byte_val [7:0] $end
$var wire 16 r half_val [15:0] $end
$var wire 32 s word_val [31:0] $end
$upscope $end
$upscope $end
$upscope $end
$enddefinitions $end

#0
$dumpvars
0!
1"
bx #
bx $
bx %
x&
bx '
bx (
bx )
bx *
bx +
bx ,
bx -
b0 .
0/
10
bx 1
bx 2
bx 3
bx 4
bx 5
bx 6
bx 7
bx 8
x9
x:
x;
x<
x=
x>
x?
x@
xA
xB
bx C
bx D
bx E
b0 F
bx G
bx H
bx I
bx J
bx K
xL
bx M
bx N
bx O
bx P
bx Q
bx0 R
bx S
bx T
b100000000 U
bx V
xW
xX
xY
xZ
x[
x\
x]
x^
x_
x`
bx a
bx b
bx c
b0 d
bx e
bx f
bx0 g
bx000000000000 h
bx0 i
bx j
bx k
bx l
xm
bx n
bx o
bx p
bx q
bx r
bx s
$end

#5000
1!
b0 #
b10011 $
b0 %
1&
b0 '
b0 (
b0 )
b0 *
b0 +
b0 ,
b0 -
1/
b0 1
b10011 2
b10011 3
b0 4
b0 5
b0 6
b0 7
b0 8
19
0:
0;
0<
0=
0>
1?
0@
0A
0B
b0 C
b0 D
b0 E
b0 G
b0 H
b0 I
b0 J
b0 K
1L
b0 M
b0 N
b100 O
b100 P
b0 Q
b0 R
b0 S
b0 T
b0 V
1W
0X
0Y
0Z
0[
0\
1]
0^
0_
0`
b0 a
b0 b
b0 c
b0 e
b0 f
b0 g
b0 h
b0 i
b0 k
b0 l
1m
b0 n
b10000000000 o
b0 p
b0 q
b0 r
b0 s

#10000
0!
0/

#15000
1!
1/
b10000000000 o

#20000
0!
0/

#25000
1!
0"
b100 #
1/
00
b100 1
b1000 O
b1000 P
b100 Q
b100 S
b100 T
b1 V

#30000
0!
0/

#35000
1!
b1000 #
1/
b1000 1
b1100 O
b1100 P
b1000 Q
b1000 S
b1000 T
b10 V

#40000
0!
0/

#45000
1!
b1100 #
1/
b1100 1
b10000 O
b10000 P
b1100 Q
b1100 S
b1100 T
b11 V

#50000
0!
0/

#55000
1!
b10000 #
1/
b10000 1
b10100 O
b10100 P
b10000 Q
b10000 S
b10000 T
b100 V

#60000
0!
0/

#65000
1!
b10100 #
1/
b10100 1
b11000 O
b11000 P
b10100 Q
b10100 S
b10100 T
b101 V

#70000
0!
0/

#75000
1!
b11000 #
1/
b11000 1
b11100 O
b11100 P
b11000 Q
b11000 S
b11000 T
b110 V

#80000
0!
0/

#85000
1!
b11100 #
1/
b11100 1
b100000 O
b100000 P
b11100 Q
b11100 S
b11100 T
b111 V

#90000
0!
0/

#95000
1!
b100000 #
1/
b100000 1
b100100 O
b100100 P
b100000 Q
b100000 S
b100000 T
b1000 V

#100000
0!
0/

#105000
1!
b100100 #
1/
b100100 1
b101000 O
b101000 P
b100100 Q
b100100 S
b100100 T
b1001 V

#110000
0!
0/

#115000
1!
b101000 #
1/
b101000 1
b101100 O
b101100 P
b101000 Q
b101000 S
b101000 T
b1010 V

#120000
0!
0/

#125000
1!
b101100 #
1/
b101100 1
b110000 O
b110000 P
b101100 Q
b101100 S
b101100 T
b1011 V

#130000
0!
0/

#135000
1!
b110000 #
1/
b110000 1
b110100 O
b110100 P
b110000 Q
b110000 S
b110000 T
b1100 V

#140000
0!
0/

#145000
1!
b110100 #
1/
b110100 1
b111000 O
b111000 P
b110100 Q
b110100 S
b110100 T
b1101 V

#150000
0!
0/

#155000
1!
b111000 #
1/
b111000 1
b111100 O
b111100 P
b111000 Q
b111000 S
b111000 T
b1110 V

#160000
0!
0/

#165000
1!
b111100 #
1/
b111100 1
b1000000 O
b1000000 P
b111100 Q
b111100 S
b111100 T
b1111 V

#170000
0!
0/

#175000
1!
b1000000 #
1/
b1000000 1
b1000100 O
b1000100 P
b1000000 Q
b1000000 S
b1000000 T
b10000 V

#180000
0!
0/

#185000
1!
b1000100 #
1/
b1000100 1
b1001000 O
b1001000 P
b1000100 Q
b1000100 S
b1000100 T
b10001 V

#190000
0!
0/

#195000
1!
b1001000 #
1/
b1001000 1
b1001100 O
b1001100 P
b1001000 Q
b1001000 S
b1001000 T
b10010 V

#200000
0!
0/

#205000
1!
b1001100 #
1/
b1001100 1
b1010000 O
b1010000 P
b1001100 Q
b1001100 S
b1001100 T
b10011 V

